tinymodbusrtu/__init__.py
tinymodbusrtu/rtumessage.py
tinymodbusrtu/tinymodbusrtu.py
tinymodbusrtu-0.1.0.dist-info/LICENSE
tinymodbusrtu-0.1.0.dist-info/METADATA
tinymodbusrtu-0.1.0.dist-info/WHEEL
tinymodbusrtu-0.1.0.dist-info/top_level.txt
tinymodbusrtu-0.1.0.dist-info/RECORD
