Metadata-Version: 2.1
Name: tinymodbusrtu
Version: 0.1.0
Summary: Modbus RTU over Serial Only
Home-page: https://tinymodbusrtu.readthedocs.io/
Author: Keil Hubbard
Author-email: keilhubbard@outlook.com
License: MIT
Classifier: Intended Audience :: Developers
Classifier: License :: OSI Approved :: MIT License
Classifier: Programming Language :: Python
Classifier: Programming Language :: Python :: 3
Classifier: Programming Language :: Python :: 3.6
Classifier: Programming Language :: Python :: 3.7
Classifier: Programming Language :: Python :: 3.8
Classifier: Programming Language :: Python :: 3.9
Classifier: Programming Language :: Python :: 3.10
Classifier: Programming Language :: Python :: 3.11
Classifier: Operating System :: OS Independent
License-File: LICENSE
Requires-Dist: pySerial
